pytmpl/__init__.py
pytmpl/__main__.py
pytmpl/cli.py
pytmpl/dialog.py
pytmpl/generator.py
pytmpl/utils/__init__.py
pytmpl/utils/tools.py
pytmpl-0.0.1.dist-info/entry_points.txt
pytmpl-0.0.1.dist-info/LICENSE
pytmpl-0.0.1.dist-info/METADATA
pytmpl-0.0.1.dist-info/WHEEL
pytmpl-0.0.1.dist-info/RECORD
